p3elf/__init__.py
p3elf/consts.py
p3elf/misc.py
p3elf/reader.py
p3elf-0.1.7.dist-info/LICENSE
p3elf-0.1.7.dist-info/METADATA
p3elf-0.1.7.dist-info/WHEEL
p3elf-0.1.7.dist-info/top_level.txt
p3elf-0.1.7.dist-info/RECORD
