Metadata-Version: 2.1
Name: p3elf
Version: 0.1.7
Summary: A tiny python3 package for parsing ELF files
Home-page: https://github.com/bool3max/p3elf/
Author: Bogdan Mitrović
Author-email: bokisa.mitrovic2@gmail.com
License: UNKNOWN
Platform: UNKNOWN
Classifier: Programming Language :: Python :: 3
Classifier: License :: OSI Approved :: MIT License
Classifier: Operating System :: OS Independent
Requires-Python: >=3.5
